typorio/__init__.py
typorio/core/__init__.py
typorio/core/commands.py
typorio/core/constants.py
typorio/core/models.py
typorio/core/worker.py
typorio/main.py
typorio/utils/__init__.py
typorio-0.1.6.dist-info/METADATA
typorio-0.1.6.dist-info/WHEEL
typorio-0.1.6.dist-info/entry_points.txt
typorio-0.1.6.dist-info/RECORD
