Metadata-Version: 2.1
Name: typorio
Version: 0.1.6
Summary: 
Author: microtypo
Author-email: microtypo.io@gmail.com
Requires-Python: >=3.10,<4.0
Classifier: Programming Language :: Python :: 3
Classifier: Programming Language :: Python :: 3.10
Classifier: Programming Language :: Python :: 3.11
Classifier: Programming Language :: Python :: 3.12
Requires-Dist: boto3 (>=1.34.114,<2.0.0)
Requires-Dist: click (>=8.1.7,<9.0.0)
Requires-Dist: pydantic (>=2.7.2,<3.0.0)
Requires-Dist: pynput (>=1.7.7,<2.0.0)
Requires-Dist: requests (>=2.32.2,<3.0.0)
